shapeshifter/__init__.py
shapeshifter/shapeshifter.py
shapeshifter/errors/__init__.py
shapeshifter/errors/columnnotfounderror.py
shapeshifter/errors/sizeexceedederror.py
shapeshifter/files/__init__.py
shapeshifter/files/arffile.py
shapeshifter/files/csvfile.py
shapeshifter/files/excelfile.py
shapeshifter/files/fwffile.py
shapeshifter/files/gctfile.py
shapeshifter/files/hdf5file.py
shapeshifter/files/htmlfile.py
shapeshifter/files/jsonfile.py
shapeshifter/files/jupyternotebookfile.py
shapeshifter/files/kallisto_est_counts_file.py
shapeshifter/files/kallisto_tpm_file.py
shapeshifter/files/msgpackfile.py
shapeshifter/files/parquetfile.py
shapeshifter/files/picklefile.py
shapeshifter/files/rmarkdownfile.py
shapeshifter/files/salmon_num_reads_file.py
shapeshifter/files/salmon_tpm_file.py
shapeshifter/files/sqlitefile.py
shapeshifter/files/ssfile.py
shapeshifter/files/statafile.py
shapeshifter/files/tsvfile.py
shapeshifter/utils/__init__.py
shapeshifter/utils/columninfo.py
shapeshifter/utils/continuousquery.py
shapeshifter/utils/convertarff.py
shapeshifter/utils/convertgct.py
shapeshifter/utils/createparquet.py
shapeshifter/utils/discretequery.py
shapeshifter/utils/filetypeenum.py
shapeshifter/utils/kallisto.py
shapeshifter/utils/mergetoparquet.py
shapeshifter/utils/operatorenum.py
shapeshifter/utils/salmon.py
shapeshifter-1.1.1.dist-info/LICENSE
shapeshifter-1.1.1.dist-info/METADATA
shapeshifter-1.1.1.dist-info/WHEEL
shapeshifter-1.1.1.dist-info/top_level.txt
shapeshifter-1.1.1.dist-info/RECORD
